<?xml version="1.0" encoding="UTF-8"?>
<?xml-stylesheet type="text/xsl" href="configuration.xsl"?>
<!-- Put site-specific property overrides in this file. -->

<configuration>
    <property>
        <name>dfs.namenode.name.dir</name>
        <value>/usr/local/hadoop/data/nameNode</value>
    </property>
    <property>
        <name>dfs.datanode.data.dir</name>
        <value>/usr/local/hadoop/data/dataNode</value>
    </property>
    <property>
      <name>dfs.namenode.checkpoint.dir</name>
      <value>/usr/local/hadoop/data/namesecondary</value>
    </property>
    <property>
		<name>dfs.namenode.secondary.http-address</name>
		<value>datanode1:9868</value>
	</property>
    <property>
		<name>dfs.namenode.http-address</name>
		<value>0.0.0.0:9870</value>
	</property>
    <property>
        <name>dfs.replication</name>
        <value>3</value>
    </property>
</configuration>